Api.py
DbContext.py
ScrapeScript.py
searchEngines.py
werkscout-0.1.0.dist-info/METADATA
werkscout-0.1.0.dist-info/WHEEL
werkscout-0.1.0.dist-info/top_level.txt
werkscout-0.1.0.dist-info/RECORD
